ostk/__init__.py
ostk/mathematics/OpenSpaceToolkitMathematicsPy.cpython-312-aarch64-linux-gnu.so
ostk/mathematics/__init__.py
ostk/mathematics/__init__.pyi
ostk/mathematics/libopen-space-toolkit-mathematics.so.4
ostk/mathematics/object.pyi
ostk/mathematics/solver.pyi
ostk/mathematics/curve_fitting/__init__.pyi
ostk/mathematics/curve_fitting/interpolator.pyi
ostk/mathematics/geometry/__init__.pyi
ostk/mathematics/geometry/d2/__init__.pyi
ostk/mathematics/geometry/d2/object.pyi
ostk/mathematics/geometry/d3/__init__.pyi
ostk/mathematics/geometry/d3/object.pyi
ostk/mathematics/geometry/d3/transformation/__init__.pyi
ostk/mathematics/geometry/d3/transformation/rotation.pyi
ostk/mathematics/test/__init__.py
ostk/mathematics/test/test_object.py
ostk/mathematics/test/curve_fitting/__init__.py
ostk/mathematics/test/curve_fitting/interpolator/__init__.py
ostk/mathematics/test/curve_fitting/interpolator/test_barycentric_rational.py
ostk/mathematics/test/curve_fitting/interpolator/test_cubic_spline.py
ostk/mathematics/test/curve_fitting/interpolator/test_interpolator.py
ostk/mathematics/test/curve_fitting/interpolator/test_linear.py
ostk/mathematics/test/geometry/__init__.py
ostk/mathematics/test/geometry/test_angle.py
ostk/mathematics/test/geometry/d2/__init__.py
ostk/mathematics/test/geometry/d2/conftest.py
ostk/mathematics/test/geometry/d2/test_object.py
ostk/mathematics/test/geometry/d2/test_transformation.py
ostk/mathematics/test/geometry/d2/object/__init__.py
ostk/mathematics/test/geometry/d2/object/test_composite.py
ostk/mathematics/test/geometry/d2/object/test_line.py
ostk/mathematics/test/geometry/d2/object/test_linestring.py
ostk/mathematics/test/geometry/d2/object/test_multipolygon.py
ostk/mathematics/test/geometry/d2/object/test_point.py
ostk/mathematics/test/geometry/d2/object/test_point_set.py
ostk/mathematics/test/geometry/d2/object/test_polygon.py
ostk/mathematics/test/geometry/d2/object/test_segment.py
ostk/mathematics/test/geometry/d3/__init__.py
open_space_toolkit_mathematics-4.5.4.dist-info/METADATA
open_space_toolkit_mathematics-4.5.4.dist-info/WHEEL
open_space_toolkit_mathematics-4.5.4.dist-info/top_level.txt
open_space_toolkit_mathematics-4.5.4.dist-info/zip-safe
open_space_toolkit_mathematics-4.5.4.dist-info/RECORD
