Metadata-Version: 2.2
Name: open-space-toolkit-mathematics
Version: 4.5.4
Summary: Geometry, curve fitting, optimization.
Author: Open Space Collective
Author-email: contact@open-space-collective.org
License: Apache License 2.0
Keywords: open-space-collective,open-space-toolkit mathematics
Classifier: Development Status :: 3 - Alpha
Classifier: Programming Language :: Python :: 3
Classifier: License :: OSI Approved :: Apache Software License
Classifier: Operating System :: POSIX :: Linux
Requires-Dist: numpy<3.0,>=1.0
Requires-Dist: open-space-toolkit-core~=5.0
